{
  "type": "minecraft:barter",
  "pools": [
    {
      "bonus_rolls": 0.0,
      "entries": [
        {
          "type": "minecraft:item",
          "functions": [
            {
              "add": false,
              "count": {
                "type": "minecraft:uniform",
                "max": 1.0,
                "min": 1.0
              },
              "function": "minecraft:set_count"
            }
          ],
          "name": "alexscaves:corrodent_teeth",
          "weight": 40
        },
        {
          "type": "minecraft:item",
          "functions": [
            {
              "add": false,
              "count": {
                "type": "minecraft:uniform",
                "max": 2.0,
                "min": 1.0
              },
              "function": "minecraft:set_count"
            }
          ],
          "name": "alexscaves:fertilizer",
          "weight": 60
        },
        {
          "type": "minecraft:item",
          "functions": [
            {
              "add": false,
              "count": {
                "type": "minecraft:uniform",
                "max": 5.0,
                "min": 3.0
              },
              "function": "minecraft:set_count"
            }
          ],
          "name": "alexscaves:guano",
          "weight": 80
        },
        {
          "type": "minecraft:item",
          "functions": [
            {
              "add": false,
              "count": {
                "type": "minecraft:uniform",
                "max": 2.0,
                "min": 1.0
              },
              "function": "minecraft:set_count"
            }
          ],
          "name": "alexscaves:burrowing_arrow",
          "weight": 50
        },
        {
          "type": "minecraft:item",
          "functions": [
            {
              "add": false,
              "count": {
                "type": "minecraft:uniform",
                "max": 4.0,
                "min": 3.0
              },
              "function": "minecraft:set_count"
            }
          ],
          "name": "alexscaves:thornwood_branch",
          "weight": 80
        },
        {
          "type": "minecraft:item",
          "functions": [
            {
              "add": false,
              "count": {
                "type": "minecraft:uniform",
                "max": 2.0,
                "min": 1.0
              },
              "function": "minecraft:set_count"
            }
          ],
          "name": "alexscaves:thornwood_log",
          "weight": 80
        },
        {
          "type": "minecraft:item",
          "functions": [
            {
              "add": false,
              "count": {
                "type": "minecraft:uniform",
                "max": 1.0,
                "min": 1.0
              },
              "function": "minecraft:set_count"
            }
          ],
          "name": "alexscaves:occult_gem",
          "weight": 5
        },
        {
          "type": "minecraft:item",
          "functions": [
            {
              "add": false,
              "count": {
                "type": "minecraft:uniform",
                "max": 1.0,
                "min": 1.0
              },
              "function": "minecraft:set_count"
            }
          ],
          "name": "alexscaves:desolate_dagger",
          "weight": 2
        },
        {
          "type": "minecraft:item",
          "functions": [
            {
              "function": "minecraft:set_nbt",
              "tag": "{Potion:\"alexscaves:haste\"}"
            }
          ],
          "name": "minecraft:potion",
          "weight": 2
        }
      ],
      "rolls": 1.0
    }
  ],
  "random_sequence": "alexscavesexemplified:entities/corrodent_trade"
}